setup.py
distributions/Binomialdistribution.py
distributions/Gaussiandistribution.py
distributions/Generaldistribution.py
distributions/__init__.py
ubajaka_distributions.egg-info/PKG-INFO
ubajaka_distributions.egg-info/SOURCES.txt
ubajaka_distributions.egg-info/dependency_links.txt
ubajaka_distributions.egg-info/not-zip-safe
ubajaka_distributions.egg-info/top_level.txt