Metadata-Version: 2.1
Name: ubajaka-distributions
Version: 0.1
Summary: Gaussian and Binomial distributions package
Author: Ubajaka Chijioke
Author-email: your_email@example.com
